pilapse/__init__.py
pilapse/__main__.py
pilapse/arguments.py
pilapse/capture.py
pilapse/cleanup.py
pilapse/compileVideo.py
pilapse/config.py
pilapse/interface.py
pilapse/logger.py
pilapserec-0.0.1.dist-info/LICENSE
pilapserec-0.0.1.dist-info/METADATA
pilapserec-0.0.1.dist-info/WHEEL
pilapserec-0.0.1.dist-info/entry_points.txt
pilapserec-0.0.1.dist-info/top_level.txt
pilapserec-0.0.1.dist-info/RECORD
