Metadata-Version: 2.1
Name: pilapserec
Version: 0.0.1
Summary: pilapse - Take time lapse videos on Raspberry Pi
Home-page: https://github.com/git-akihakune/pilapse
Author: akihakune
Author-email: akihakune@gmail.com
License: MIT
Keywords: timelapse video pilapse picamera raspberrypi
Platform: UNKNOWN
Classifier: Development Status :: 2 - Pre-Alpha
Classifier: Environment :: Console
Classifier: Intended Audience :: End Users/Desktop
Classifier: License :: OSI Approved :: MIT License
Classifier: Natural Language :: English
Classifier: Operating System :: POSIX :: Linux
Classifier: Programming Language :: Python :: 3.9
Classifier: Topic :: Utilities
Classifier: Topic :: Multimedia :: Video :: Capture
Requires-Dist: docopt
Requires-Dist: moviepy
Requires-Dist: picamera
Requires-Dist: tqdm
